{
  "team1_id": 542,
  "team2_id": 798,
  "fetched_at": "2026-04-19T17:18:35.519Z",
  "played": 9,
  "team1_wins": 2,
  "team2_wins": 4,
  "draws": 3,
  "team1_goals": 6,
  "team2_goals": 7,
  "last_matches": [
    {
      "fixture_id": 1390885,
      "date": "2025-09-27",
      "league": "La Liga",
      "home_id": 798,
      "home_name": "Mallorca",
      "home_logo": "https://media.api-sports.io/football/teams/798.png",
      "away_id": 542,
      "away_name": "Alaves",
      "away_logo": "https://media.api-sports.io/football/teams/542.png",
      "home_score": 1,
      "away_score": 0
    },
    {
      "fixture_id": 1208727,
      "date": "2025-03-02",
      "league": "La Liga",
      "home_id": 798,
      "home_name": "Mallorca",
      "home_logo": "https://media.api-sports.io/football/teams/798.png",
      "away_id": 542,
      "away_name": "Alaves",
      "away_logo": "https://media.api-sports.io/football/teams/542.png",
      "home_score": 1,
      "away_score": 1
    },
    {
      "fixture_id": 1208598,
      "date": "2024-11-01",
      "league": "La Liga",
      "home_id": 542,
      "home_name": "Alaves",
      "home_logo": "https://media.api-sports.io/football/teams/542.png",
      "away_id": 798,
      "away_name": "Mallorca",
      "away_logo": "https://media.api-sports.io/football/teams/798.png",
      "home_score": 1,
      "away_score": 0
    },
    {
      "fixture_id": 1038210,
      "date": "2024-02-24",
      "league": "La Liga",
      "home_id": 542,
      "home_name": "Alaves",
      "home_logo": "https://media.api-sports.io/football/teams/542.png",
      "away_id": 798,
      "away_name": "Mallorca",
      "away_logo": "https://media.api-sports.io/football/teams/798.png",
      "home_score": 1,
      "away_score": 1
    },
    {
      "fixture_id": 1038101,
      "date": "2023-12-03",
      "league": "La Liga",
      "home_id": 798,
      "home_name": "Mallorca",
      "home_logo": "https://media.api-sports.io/football/teams/798.png",
      "away_id": 542,
      "away_name": "Alaves",
      "away_logo": "https://media.api-sports.io/football/teams/542.png",
      "home_score": 0,
      "away_score": 0
    },
    {
      "fixture_id": 721062,
      "date": "2022-04-19",
      "league": "La Liga",
      "home_id": 798,
      "home_name": "Mallorca",
      "home_logo": "https://media.api-sports.io/football/teams/798.png",
      "away_id": 542,
      "away_name": "Alaves",
      "away_logo": "https://media.api-sports.io/football/teams/542.png",
      "home_score": 2,
      "away_score": 1
    },
    {
      "fixture_id": 720749,
      "date": "2021-08-21",
      "league": "La Liga",
      "home_id": 542,
      "home_name": "Alaves",
      "home_logo": "https://media.api-sports.io/football/teams/542.png",
      "away_id": 798,
      "away_name": "Mallorca",
      "away_logo": "https://media.api-sports.io/football/teams/798.png",
      "home_score": 0,
      "away_score": 1
    },
    {
      "fixture_id": 214257,
      "date": "2020-02-15",
      "league": "La Liga",
      "home_id": 798,
      "home_name": "Mallorca",
      "home_logo": "https://media.api-sports.io/football/teams/798.png",
      "away_id": 542,
      "away_name": "Alaves",
      "away_logo": "https://media.api-sports.io/football/teams/542.png",
      "home_score": 1,
      "away_score": 0
    },
    {
      "fixture_id": 214082,
      "date": "2019-09-29",
      "league": "La Liga",
      "home_id": 542,
      "home_name": "Alaves",
      "home_logo": "https://media.api-sports.io/football/teams/542.png",
      "away_id": 798,
      "away_name": "Mallorca",
      "away_logo": "https://media.api-sports.io/football/teams/798.png",
      "home_score": 2,
      "away_score": 0
    }
  ]
}