{
  "team1_id": 79,
  "team2_id": 108,
  "fetched_at": "2026-04-19T17:19:09.654Z",
  "played": 10,
  "team1_wins": 5,
  "team2_wins": 1,
  "draws": 4,
  "team1_goals": 21,
  "team2_goals": 12,
  "last_matches": [
    {
      "fixture_id": 1387834,
      "date": "2025-12-14",
      "league": "Ligue 1",
      "home_id": 108,
      "home_name": "Auxerre",
      "home_logo": "https://media.api-sports.io/football/teams/108.png",
      "away_id": 79,
      "away_name": "Lille",
      "away_logo": "https://media.api-sports.io/football/teams/79.png",
      "home_score": 3,
      "away_score": 4
    },
    {
      "fixture_id": 1214011,
      "date": "2025-04-20",
      "league": "Ligue 1",
      "home_id": 79,
      "home_name": "Lille",
      "home_logo": "https://media.api-sports.io/football/teams/79.png",
      "away_id": 108,
      "away_name": "Auxerre",
      "away_logo": "https://media.api-sports.io/football/teams/108.png",
      "home_score": 3,
      "away_score": 1
    },
    {
      "fixture_id": 1213893,
      "date": "2025-01-10",
      "league": "Ligue 1",
      "home_id": 108,
      "home_name": "Auxerre",
      "home_logo": "https://media.api-sports.io/football/teams/108.png",
      "away_id": 79,
      "away_name": "Lille",
      "away_logo": "https://media.api-sports.io/football/teams/79.png",
      "home_score": 0,
      "away_score": 0
    },
    {
      "fixture_id": 871781,
      "date": "2023-04-22",
      "league": "Ligue 1",
      "home_id": 108,
      "home_name": "Auxerre",
      "home_logo": "https://media.api-sports.io/football/teams/108.png",
      "away_id": 79,
      "away_name": "Lille",
      "away_logo": "https://media.api-sports.io/football/teams/79.png",
      "home_score": 1,
      "away_score": 1
    },
    {
      "fixture_id": 871475,
      "date": "2022-08-07",
      "league": "Ligue 1",
      "home_id": 79,
      "home_name": "Lille",
      "home_logo": "https://media.api-sports.io/football/teams/79.png",
      "away_id": 108,
      "away_name": "Auxerre",
      "away_logo": "https://media.api-sports.io/football/teams/108.png",
      "home_score": 4,
      "away_score": 1
    },
    {
      "fixture_id": 814263,
      "date": "2021-12-18",
      "league": "Coupe de France",
      "home_id": 79,
      "home_name": "Lille",
      "home_logo": "https://media.api-sports.io/football/teams/79.png",
      "away_id": 108,
      "away_name": "Auxerre",
      "away_logo": "https://media.api-sports.io/football/teams/108.png",
      "home_score": 3,
      "away_score": 1
    },
    {
      "fixture_id": 527531,
      "date": "2013-10-29",
      "league": "Coupe de la Ligue",
      "home_id": 79,
      "home_name": "Lille",
      "home_logo": "https://media.api-sports.io/football/teams/79.png",
      "away_id": 108,
      "away_name": "Auxerre",
      "away_logo": "https://media.api-sports.io/football/teams/108.png",
      "home_score": 0,
      "away_score": 1
    },
    {
      "fixture_id": 187316,
      "date": "2012-03-03",
      "league": "Ligue 1",
      "home_id": 79,
      "home_name": "Lille",
      "home_logo": "https://media.api-sports.io/football/teams/79.png",
      "away_id": 108,
      "away_name": "Auxerre",
      "away_logo": "https://media.api-sports.io/football/teams/108.png",
      "home_score": 2,
      "away_score": 2
    },
    {
      "fixture_id": 187155,
      "date": "2011-10-15",
      "league": "Ligue 1",
      "home_id": 108,
      "home_name": "Auxerre",
      "home_logo": "https://media.api-sports.io/football/teams/108.png",
      "away_id": 79,
      "away_name": "Lille",
      "away_logo": "https://media.api-sports.io/football/teams/79.png",
      "home_score": 1,
      "away_score": 3
    },
    {
      "fixture_id": 187662,
      "date": "2011-02-06",
      "league": "Ligue 1",
      "home_id": 108,
      "home_name": "Auxerre",
      "home_logo": "https://media.api-sports.io/football/teams/108.png",
      "away_id": 79,
      "away_name": "Lille",
      "away_logo": "https://media.api-sports.io/football/teams/79.png",
      "home_score": 1,
      "away_score": 1
    }
  ]
}