{
  "player_id": 278,
  "slug": "kylian-mbappe",
  "name": "Kylian Mbappé",
  "api_photo": "https://media.api-sports.io/football/players/278.png",
  "seasons": [
    {
      "season": 2024,
      "club": "Real Madrid",
      "club_logo": "https://media.api-sports.io/football/teams/541.png",
      "league": "La Liga",
      "league_id": 140,
      "appearances": 34,
      "goals": 31,
      "assists": 3,
      "minutes": 2917,
      "yellow_cards": 3,
      "red_cards": 1
    },
    {
      "season": 2024,
      "club": "Real Madrid",
      "club_logo": "https://media.api-sports.io/football/teams/541.png",
      "league": "UEFA Champions League",
      "league_id": 2,
      "appearances": 14,
      "goals": 7,
      "assists": 1,
      "minutes": 1134,
      "yellow_cards": 1,
      "red_cards": 0
    }
  ]
}
